llmocal/__init__.py
llmocal/cli.py
llmocal/api/__init__.py
llmocal/core/__init__.py
llmocal/core/chat.py
llmocal/core/config.py
llmocal/core/engine.py
llmocal/models/__init__.py
llmocal/models/manager.py
llmocal/ui/__init__.py
llmocal/utils/__init__.py
llmocal-4.1.1.dist-info/licenses/LICENSE
llmocal-4.1.1.dist-info/METADATA
llmocal-4.1.1.dist-info/WHEEL
llmocal-4.1.1.dist-info/entry_points.txt
llmocal-4.1.1.dist-info/top_level.txt
llmocal-4.1.1.dist-info/RECORD
