Metadata-Version: 2.4
Name: llmocal
Version: 4.1.1
Summary: Professional open source client for running large language models locally
Author-email: Alex Nicita <alex@llmocal.dev>
Maintainer-email: Alex Nicita <alex@llmocal.dev>
License-Expression: MIT
Project-URL: Homepage, https://github.com/alexnicita/llmocal
Project-URL: Repository, https://github.com/alexnicita/llmocal.git
Project-URL: Issues, https://github.com/alexnicita/llmocal/issues
Project-URL: Changelog, https://github.com/alexnicita/llmocal/blob/main/CHANGELOG.md
Project-URL: Documentation, https://github.com/alexnicita/llmocal#readme
Keywords: llm,ai,local,language-model,chat,offline,privacy,llama,mistral,gguf
Classifier: Development Status :: 3 - Alpha
Classifier: Intended Audience :: Developers
Classifier: Intended Audience :: End Users/Desktop
Classifier: Intended Audience :: Science/Research
Classifier: Operating System :: OS Independent
Classifier: Programming Language :: Python :: 3
Classifier: Programming Language :: Python :: 3.11
Classifier: Programming Language :: Python :: 3.12
Classifier: Programming Language :: Python :: 3.13
Classifier: Topic :: Scientific/Engineering :: Artificial Intelligence
Classifier: Topic :: Software Development :: Libraries :: Python Modules
Classifier: Topic :: Communications :: Chat
Classifier: Topic :: Internet :: WWW/HTTP :: Dynamic Content
Requires-Python: >=3.11
License-File: LICENSE
Requires-Dist: huggingface-hub>=0.34.3
Requires-Dist: llama-cpp-python>=0.3.14
Requires-Dist: rich>=14.1.0
Requires-Dist: typing-extensions>=4.14.1
Requires-Dist: click>=8.1.0
Requires-Dist: pydantic>=2.5.0
Requires-Dist: pydantic-settings>=2.0.0
Requires-Dist: fastapi>=0.104.0
Requires-Dist: uvicorn>=0.24.0
Dynamic: license-file
